nampy/__init__.py
nampy/programs.py
nampy/programs_old.py
nampy_ml-0.0.2.dist-info/METADATA
nampy_ml-0.0.2.dist-info/WHEEL
nampy_ml-0.0.2.dist-info/entry_points.txt
nampy_ml-0.0.2.dist-info/top_level.txt
nampy_ml-0.0.2.dist-info/RECORD
