Metadata-Version: 2.4
Name: nampy-ml
Version: 0.0.2
Summary: ML Lab programs library showing code
Author: Vamshi
License: MIT
Project-URL: Homepage, https://pypi.org/project/nampy-ml/
Requires-Python: >=3.8
